test/__init__.py
test/test_access_control_element.py
test/test_access_control_list_read_dto.py
test/test_access_control_list_simple.py
test/test_access_control_list_write_dto.py
test/test_access_policy.py
test/test_access_policy_api.py
test/test_access_policy_rule_dto.py
test/test_account.py
test/test_account__user_and_service_account_api.py
test/test_alert.py
test/test_alert_analytics_summary.py
test/test_alert_analytics_summary_detail.py
test/test_alert_api.py
test/test_alert_dashboard.py
test/test_alert_error_group_info.py
test/test_alert_error_group_summary.py
test/test_alert_error_summary.py
test/test_alert_min.py
test/test_alert_route.py
test/test_alert_source.py
test/test_annotation.py
test/test_anomaly.py
test/test_api_token_api.py
test/test_api_token_model.py
test/test_app_dynamics_configuration.py
test/test_app_search_filter.py
test/test_app_search_filter_value.py
test/test_app_search_filters.py
test/test_aws_base_credentials.py
test/test_azure_activity_log_configuration.py
test/test_azure_base_credentials.py
test/test_azure_configuration.py
test/test_chart.py
test/test_chart_settings.py
test/test_chart_source_query.py
test/test_class_loader.py
test/test_cloud_integration.py
test/test_cloud_integration_api.py
test/test_cloud_trail_configuration.py
test/test_cloud_watch_configuration.py
test/test_cluster_info_dto.py
test/test_conversion.py
test/test_conversion_object.py
test/test_customer_facing_user_object.py
test/test_dashboard.py
test/test_dashboard_api.py
test/test_dashboard_min.py
test/test_dashboard_parameter_value.py
test/test_dashboard_section.py
test/test_dashboard_section_row.py
test/test_default_saved_app_map_search.py
test/test_default_saved_traces_search.py
test/test_derived_metric_api.py
test/test_derived_metric_definition.py
test/test_direct_ingestion_api.py
test/test_dynatrace_configuration.py
test/test_ec2_configuration.py
test/test_event.py
test/test_event_api.py
test/test_event_search_request.py
test/test_event_time_range.py
wavefront_api_client-2.202.2.dist-info/LICENSE
wavefront_api_client-2.202.2.dist-info/METADATA
wavefront_api_client-2.202.2.dist-info/WHEEL
wavefront_api_client-2.202.2.dist-info/top_level.txt
wavefront_api_client-2.202.2.dist-info/RECORD
