Metadata-Version: 2.1
Name: wavefront-api-client
Version: 2.202.2
Summary: Wavefront REST API Documentation
Home-page: https://github.com/wavefrontHQ/python-client
Author-email: chitimba@wavefront.com
Keywords: Swagger,Wavefront REST API Documentation
License-File: LICENSE
Requires-Dist: certifi >=2017.4.17
Requires-Dist: python-dateutil >=2.1
Requires-Dist: six >=1.10
Requires-Dist: urllib3 >=1.23
